onnxisolation/__init__.py
onnxisolation/export.py
onnxisolation/get_shape.py
onnxisolation/isolate.py
onnxisolation/reshape.py
onnxisolation-1.0.0.dist-info/LICENSE
onnxisolation-1.0.0.dist-info/METADATA
onnxisolation-1.0.0.dist-info/WHEEL
onnxisolation-1.0.0.dist-info/top_level.txt
onnxisolation-1.0.0.dist-info/RECORD
