Metadata-Version: 2.1
Name: onnxisolation
Version: 1.0.0
Summary: To isolate onnx.
Home-page: https://github.com/ch98road/onnxisolation
Author: chenhuan
Author-email: chenhuan21s@ict.ac.cn
Keywords: onnx isolate shape
Classifier: Development Status :: 3 - Alpha
Classifier: Intended Audience :: Developers
Classifier: Topic :: Software Development :: Build Tools
Classifier: Programming Language :: Python :: 3
License-File: LICENSE
Requires-Dist: nvidia-pyindex
Requires-Dist: numpy
Requires-Dist: onnx
Requires-Dist: onnx-graphsurgeon
Requires-Dist: onnxoptimizer
Requires-Dist: onnxruntime
